{"nodes": [{"id": "assetspage", "label": "AssetsPage.tsx", "file_type": "code", "source_file": "frontend/src/pages/AssetsPage.tsx", "source_location": "L1"}], "edges": [{"source": "assetspage", "target": "useassets", "relation": "imports_from", "confidence": "EXTRACTED", "source_file": "frontend/src/pages/AssetsPage.tsx", "source_location": "L1", "weight": 1.0}, {"source": "assetspage", "target": "assetpricerow", "relation": "imports_from", "confidence": "EXTRACTED", "source_file": "frontend/src/pages/AssetsPage.tsx", "source_location": "L2", "weight": 1.0}, {"source": "assetspage", "target": "loadingskeleton", "relation": "imports_from", "confidence": "EXTRACTED", "source_file": "frontend/src/pages/AssetsPage.tsx", "source_location": "L3", "weight": 1.0}, {"source": "assetspage", "target": "errorbanner", "relation": "imports_from", "confidence": "EXTRACTED", "source_file": "frontend/src/pages/AssetsPage.tsx", "source_location": "L4", "weight": 1.0}]}